0 LOAD_CONST int
1 PUSH_GLOBAL num
2 LOAD_CONST int
3 PUSH_GLOBAL num2
4 LOAD_CONST string
5 PUSH_GLOBAL a
6 LOAD_CONST boolean
7 PUSH_GLOBAL b
8 LOAD_CONST int
9 PUSH_GLOBAL temp
10 DEF
11 PUSH_LOCAL x
12 LOAD_CONST int
13 PUSH_LOCAL sum
14 LOAD_CONST 1
15 STORE_FAST
16 LOAD_CONST 2
17 STORE_FAST
18 JUMP_IF_FALSE 28
19 LOAD_FAST
20 LOAD_FAST
21 LOAD_CONST 1
22 BINARY_ADD
23 LOAD_GLOBAL
24 CALL_FUNCTION 1
25 BINARY_ADD
26 STORE_FAST
27 JUMP_ABSOLUTE 30
28 LOAD_CONST 0
29 STORE_FAST
30 RETURN_VALUE
31 RETURN
32 DEF Main
33 LOAD_CONST 1
34 STORE_FAST
35 LOAD_CONST 1
36 STORE_FAST
37 LOAD_CONST 0
38 STORE_FAST
40 JUMP_ABSOLUTE 59
40 STORE_FAST
41 LOAD_FAST
42 LOAD_FAST
43 BINARY_ADD
44 LOAD_FAST
45 BINARY_ADD
46 LOAD_CONST 2
47 BINARY_ADD
48 LOAD_CONST 5
49 BINARY_ADD
50 STORE_FAST
51 LOAD_FAST
52 LOAD_FAST
53 BINARY_ADD
54 STORE_FAST
55 LOAD_FAST
56 LOAD_CONST 1
57 BINARY_ADD
58 STORE_FAST
59 JUMP_IF_TRUE 40
60 END
